pdp/__init__.py
pdp/cli.py
pdp/pdp.py
pdp/pdp_config.py
pdp/pdp_errors.py
pdp/snakemake_executor.py
pdp/task.py
pdp_helper-0.1.0.dist-info/LICENSE.md
pdp_helper-0.1.0.dist-info/METADATA
pdp_helper-0.1.0.dist-info/WHEEL
pdp_helper-0.1.0.dist-info/entry_points.txt
pdp_helper-0.1.0.dist-info/RECORD
