Metadata-Version: 2.3
Name: pdp-helper
Version: 0.1.0
Summary: Principled Data Processing CLI tool
License: GPL-3.0-or-later
Author: Sam Zhang
Author-email: sam.zhang@uvm.edu
Requires-Python: >=3.11
Classifier: License :: OSI Approved :: GNU General Public License v3 or later (GPLv3+)
Classifier: Programming Language :: Python :: 3
Classifier: Programming Language :: Python :: 3.11
Classifier: Programming Language :: Python :: 3.12
Classifier: Programming Language :: Python :: 3.13
Requires-Dist: rich (>=14.0.0,<15.0.0)
Requires-Dist: ruamel-yaml (>=0.18.10,<0.19.0)
Requires-Dist: typer (>=0.15.2,<0.16.0)
